<?xml version="1.0" encoding="UTF-8"?>
<?oxygen RNGSchema="shared/cpf.rng" type="xml"?>
<eac-cpf xmlns="urn:isbn:1-931666-33-4" xmlns:xlink="http://www.w3.org/1999/xlink" xmlns:xsi="http://www.w3.org/2001/XMLSchema-instance" xsi:schemaLocation="urn:isbn:1-931666-33-4 http://eac.staatsbibliothek-berlin.de/schema/cpf.xsd">
<control>
<recordId>EM00512</recordId>
<maintenanceStatus>revised</maintenanceStatus>
<maintenanceAgency>
<agencyCode>AU-EMEL</agencyCode>
<agencyName>eMelbourne - The Encyclopedia of Melbourne Online</agencyName>
<descriptiveNote>
<p></p>
</descriptiveNote>
</maintenanceAgency>
<languageDeclaration>
<language languageCode="eng">English</language>
<script scriptCode="Latn">Latin</script>
</languageDeclaration>
<conventionDeclaration>
<abbreviation>AACR2</abbreviation>
<citation>Anglo-American Cataloguing Rules</citation>
</conventionDeclaration>
<localControl localType="typeOfEntity">
<term>Entry</term>
</localControl>
<maintenanceHistory>
<maintenanceEvent>
<eventType>created</eventType>
<eventDateTime standardDateTime="2008-06-26">2008-06-26</eventDateTime>
<agentType>human</agentType>
<agent>Maryanne Mccubbin</agent>
<eventDescription></eventDescription>
</maintenanceEvent>
<maintenanceEvent>
<eventType>updated</eventType>
<eventDateTime standardDateTime="2008-08-08">2008-08-08</eventDateTime>
<agentType>human</agentType>
<agent></agent>
<eventDescription></eventDescription>
</maintenanceEvent>
</maintenanceHistory>
</control>
<cpfDescription>
<identity><entityId>http://www.emelbourne.net.au/biogs/EM00512b.htm</entityId>
<entityType>concept</entityType>
<nameEntry><part>Eight Hours' Day Monument</part>
<authorizedForm>AACR2</authorizedForm>
</nameEntry>
</identity>
<description><places>
</places>
<biogHist>
<abstract>A memorial to the Eight Hours' Day movement stands on a reserve at the corner of Victoria and Lygon streets, Carlton. In 1890, parliament granted the pioneers of the movement a site at the north-west corner of Spring Street and Carpentaria Place. Percival Ball's original design depicted 'a workman and the goddess Liberty holding a torch aloft'. Seeking £3000 by donation, the pioneers laid the foundation stone on 21 April 1891, the 35th anniversary of the gaining of the eight hours' day. Upon Ball's death in 1900, the Pioneers of the Eight Hour Movement Committee reworked his design, to be erected for £800. Ball's pedestal and granite column was framed above by three figure 8s, topped by a sphere representing the earth inscribed with the words 'Rest, Labour and Recreation'. The monument was unveiled on 21 April 1903. The route of the Eight Hours' Day procession was altered in 1923, and in 1924 the monument was moved to its current location. It continues to serve as a major symbolic gathering place for the labour movement on Labour Day, May Day and during other industrial protests and marches. 

</abstract>

</biogHist>
</description>
<relations><resourceRelation resourceRelationType="subjectOf">
<relationEntry localType="published">'Eight Hours' Day Monument', in <span style="font-style:italic">eMelbourne - The Encyclopedia of Melbourne Online</span>, School of Historical Studies, Department of History, The University of Melbourne</relationEntry>

<objectXMLWrap>
<bibref xmlns="urn:isbn:1-931666-22-9">
<title render="italic">Eight Hours' Day Monument</title>
<imprint>
<publisher>School of Historical Studies<br /> Department of History, The University of Melbourne</publisher>
</imprint>
<bibseries>
<title render="italic">eMelbourne - The Encyclopedia of Melbourne Online</title>
</bibseries>
<extptr linktype="simple" href="http://www.emelbourne.net.au/biogs/EM00512b.htm"></extptr>
</bibref>
</objectXMLWrap>
</resourceRelation>
<resourceRelation resourceRelationType="other" xlink:type="simple" xlink:href="http://www.emelbourne.net.au/objects/D00000060.htm">
<relationEntry localType="digitalObject">Eight Hour Day Memorial</relationEntry>

<objectXMLWrap>
<archref xmlns="urn:isbn:1-931666-22-9">
<unittitle>Eight Hour Day Memorial</unittitle>
<unitdate>1900 - 1903</unitdate>
<physdesc>Granite, bronze and gold-leaf monument with stone pedestal<geogname>

Corner of Russell and Victoria Streets</geogname>
</physdesc>
<note label="rights">Courtesy City of Melbourne</note>
</archref>
</objectXMLWrap>

<descriptiveNote>
<p>Include in Gallery</p>
</descriptiveNote>
</resourceRelation>
</relations>
</cpfDescription>
</eac-cpf>
